setup.py
aria2Agent.egg-info/PKG-INFO
aria2Agent.egg-info/SOURCES.txt
aria2Agent.egg-info/dependency_links.txt
aria2Agent.egg-info/entry_points.txt
aria2Agent.egg-info/requires.txt
aria2Agent.egg-info/top_level.txt
aria2_agent/__init__.py
aria2_agent/agent.py
aria2_agent/main.py
aria2_agent/api/__init__.py
aria2_agent/api/aria2_api.py
aria2_agent/mq/__init__.py
aria2_agent/mq/mq_client.py
aria2_agent/websocket_rpc/__init__.py
aria2_agent/websocket_rpc/aria2_websocket.py