Metadata-Version: 1.1
Name: aria2Agent
Version: 0.0.1.4
Summary: aria2 agent
Home-page: UNKNOWN
Author: Exception
Author-email: webmaster@pocketdigi.com
License: MIT
Keywords: aria2 download
Platform: any
Classifier: Development Status :: 3 - Alpha
Classifier: Intended Audience :: Developers
Classifier: Topic :: Internet
Classifier: License :: Free For Home Use
Classifier: Programming Language :: Python :: 2.6
Classifier: Programming Language :: Python :: 2.7
